beholder_client/__init__.py
beholder_client/client.py
beholder_client/ops.py
beholder_client-0.3.1.dist-info/LICENSE
beholder_client-0.3.1.dist-info/METADATA
beholder_client-0.3.1.dist-info/WHEEL
beholder_client-0.3.1.dist-info/RECORD
