Metadata-Version: 2.1
Name: beholder_client
Version: 0.3.1
Summary: Python client library for beholder.
Home-page: https://github.com/mbari-org/beholder-py
License: MIT
Author: Kevin Barnard
Author-email: kbarnard@mbari.org
Requires-Python: >=3.9,<4.0
Classifier: License :: OSI Approved :: MIT License
Classifier: Programming Language :: Python :: 3
Classifier: Programming Language :: Python :: 3.9
Classifier: Programming Language :: Python :: 3.10
Classifier: Programming Language :: Python :: 3.11
Classifier: Programming Language :: Python :: 3.12
Requires-Dist: Pillow (>=9.2.0)
Requires-Dist: httpx (>=0.28.1,<0.29.0)
Project-URL: Repository, https://github.com/mbari-org/beholder-py
